linearinit/__init__.py
linearinit/base.py
linearinit-0.2.0.dist-info/LICENSE
linearinit-0.2.0.dist-info/METADATA
linearinit-0.2.0.dist-info/WHEEL
linearinit-0.2.0.dist-info/top_level.txt
linearinit-0.2.0.dist-info/RECORD
