Metadata-Version: 2.1
Name: linearinit
Version: 0.2.0
Summary: nn.linear with initialization created by nxdens
Home-page: https://github.com/nxdens/linearInit/
Author: nxdens
License-File: LICENSE
Requires-Dist: torch >=2.0.1
Requires-Dist: pytest >=7.1.0
Requires-Dist: numpy >=1.24.1
Requires-Dist: coverage
Requires-Dist: flake8
Requires-Dist: black
Requires-Dist: isort
Requires-Dist: pytest-cov
Requires-Dist: mypy
Requires-Dist: gitchangelog
Requires-Dist: mkdocs
Provides-Extra: test
Requires-Dist: pytest ; extra == 'test'
Requires-Dist: coverage ; extra == 'test'
Requires-Dist: flake8 ; extra == 'test'
Requires-Dist: black ; extra == 'test'
Requires-Dist: isort ; extra == 'test'
Requires-Dist: pytest-cov ; extra == 'test'
Requires-Dist: mypy ; extra == 'test'
Requires-Dist: gitchangelog ; extra == 'test'
Requires-Dist: mkdocs ; extra == 'test'
